bhavya_resume_generator/__init__.py
bhavya_resume_generator/generator.py
bhavya_resume_generator/examples/basic_example.py
bhavya_resume_generator-0.1.3.dist-info/licenses/LICENSE
bhavya_resume_generator-0.1.3.dist-info/METADATA
bhavya_resume_generator-0.1.3.dist-info/WHEEL
bhavya_resume_generator-0.1.3.dist-info/top_level.txt
bhavya_resume_generator-0.1.3.dist-info/RECORD
