Metadata-Version: 2.4
Name: bhavya-resume-generator
Version: 0.1.3
Summary: A Python package to generate professional resumes in Word format
Home-page: https://github.com/yourusername/resume-generator
Author: Bhavya Gada
Author-email: your.email@example.com
Classifier: Programming Language :: Python :: 3
Classifier: License :: OSI Approved :: MIT License
Classifier: Operating System :: OS Independent
Requires-Python: >=3.6
License-File: LICENSE
Requires-Dist: python-docx>=0.8.11
Dynamic: author
Dynamic: author-email
Dynamic: classifier
Dynamic: description
Dynamic: description-content-type
Dynamic: home-page
Dynamic: license-file
Dynamic: requires-dist
Dynamic: requires-python
Dynamic: summary
